{
      "session_file": "13434383452",
      "phone": "13434383452",
      "register_time": 1732711412,
      "app_id": 659337,
      "app_hash": "314703a39f45937dcdee8dbb8c2dacbb",
      "sdk": "SDK 31",
      "app_version": "11.2.6 (1102061)",
      "device": "Samsung SM-M315F",
      "last_check_time": 1732711412,
      "first_name": "Brittany",
      "last_name": "Kalyani",
      "system_lang_code": "en-CA",
      "lang_code": "en",
      "twoFA": "83452",
      "proxy": null,
      "ipv6": false,
      "username": null,
      "avatar": "img/default.png"
}