{
      "session_file": "639104525531",
      "phone": "639104525531",
      "register_time": 1728298699,
      "app_id": 659337,
      "app_hash": "314703a39f45937dcdee8dbb8c2dacbb",
      "sdk": "SDK 31",
      "app_version": "11.1.4 (1101040)",
      "device": "Samsung SM-N985F",
      "last_check_time": 1728298699,
      "first_name": "Travis",
      "last_name": "Epps",
      "system_lang_code": "en-PH",
      "lang_code": "en",
      "twoFA": "25531",
      "proxy": null,
      "ipv6": false,
      "username": null,
      "avatar": "img/default.png"
}