{
      "session_file": "639284359164",
      "phone": "639284359164",
      "register_time": 1728644876,
      "app_id": 659337,
      "app_hash": "314703a39f45937dcdee8dbb8c2dacbb",
      "sdk": "SDK 31",
      "app_version": "11.1.5 (1101050)",
      "device": "Samsung SM-M115F",
      "last_check_time": 1728644876,
      "first_name": "James",
      "last_name": "Vaillancourt",
      "system_lang_code": "en-PH",
      "lang_code": "en",
      "twoFA": "59164",
      "proxy": null,
      "ipv6": false,
      "username": null,
      "avatar": "img/default.png"
}