{
      "session_file": "639106565244",
      "phone": "639106565244",
      "register_time": 1732704879,
      "app_id": 659337,
      "app_hash": "314703a39f45937dcdee8dbb8c2dacbb",
      "sdk": "SDK 31",
      "app_version": "11.2.6 (1102061)",
      "device": "Samsung SM-A315F",
      "last_check_time": 1732704879,
      "first_name": "Darius",
      "last_name": "Skeet",
      "system_lang_code": "en-PH",
      "lang_code": "en",
      "twoFA": "65244",
      "proxy": null,
      "ipv6": false,
      "username": null,
      "avatar": "img/default.png"
}